safehtml/__init__.py
safehtml-1.0.1.dist-info/licenses/LICENSE
safehtml-1.0.1.dist-info/METADATA
safehtml-1.0.1.dist-info/WHEEL
safehtml-1.0.1.dist-info/top_level.txt
safehtml-1.0.1.dist-info/RECORD
