Metadata-Version: 2.4
Name: safehtml
Version: 1.0.1
Summary: Escape HTML with style using T-Strings!
Requires-Python: >=3.14
License-File: LICENSE
Dynamic: license-file
